Metadata-Version: 2.1
Name: django-transactional-notifications
Version: 0.3.4
Summary: Send transactional notifications to any service.
Home-page: https://gitlab.com/rogeliomtx/django-notifications
Author: Rogelio Martínez
Author-email: hi@rogermx.com
License: MIT
Keywords: django notifications email twilio mailgun transactional messages webhooks
Classifier: Development Status :: 5 - Production/Stable
Classifier: Environment :: Web Environment
Classifier: Framework :: Django
Classifier: Intended Audience :: Developers
Classifier: License :: OSI Approved :: BSD License
Classifier: Operating System :: OS Independent
Classifier: Framework :: Django
Classifier: Framework :: Django :: 3.0
Classifier: Framework :: Django :: 4.0
Classifier: Programming Language :: Python
Classifier: Programming Language :: Python :: 3
Classifier: Programming Language :: Python :: 3.6
Classifier: Programming Language :: Python :: 3.7
Classifier: Programming Language :: Python :: 3.8
Classifier: Programming Language :: Python :: 3.9
Classifier: Topic :: Utilities
License-File: LICENCE
Requires-Dist: django (>=2.2)
Requires-Dist: swapper
Requires-Dist: markdown
Requires-Dist: beautifulsoup4
